{
  "ps": {
    "卷號": "45",
    "篇號": "1204",
    "篇名": "捨一切喜歡"
  },
  "起": "如是我聞：一時，佛住舍衛國祇樹給孤獨園。",
  "法": [
    "時，有毘闍耶比丘尼住舍衛國王園比丘尼眾中，晨朝著衣持鉢入舍衛城乞食，食已還精舍，舉衣鉢洗足畢持尼師壇著肩上入安陀林，坐一樹下，入晝正受。時，魔波旬作是念：「此沙門瞿曇住舍衛國祇樹給孤獨園，弟子毘闍耶比丘尼住舍衛國王園比丘尼眾中，晨朝著衣持鉢入舍衛城乞食，食已還精舍，舉衣鉢洗足畢持尼師壇著肩上入安陀林，坐一樹下，入晝正受，我今當往為作留難。」即化作年少，容貌端正，往至其前而說偈言：「汝今年幼少，我亦是年少，當共於此處，作五種音樂，而共相娛樂，用是禪思為？」",
    "時，毘闍耶比丘尼作是念：「此何等人欲恐怖我？為是人耶為非人耶為姦狡人耶？」如是思惟已即得知覺：「是魔波旬欲作嬈亂。」即說偈言：「歌舞作眾伎，種種相娛樂，今悉已惠汝，非我之所須。若寂滅正受，及天人五欲，一切持相與，亦非我所須。捨一切喜歡，離一切闇冥，寂滅以作證，安住諸漏盡。已知汝惡魔，當自消滅去。」"
  ],
  "結": "時，魔波旬作是念：「是毘闍耶比丘尼已知我心。」內懷憂慼，即沒不現。",
  "fu": {
    "摘": "歌舞作眾伎，種種相娛樂，今悉已惠汝，非我之所須。若寂滅正受，及天人五欲，一切持相與，亦非我所須。捨一切喜歡，離一切闇冥，寂滅以作證，安住諸漏盡。"
  }
}