{
  "ps": {
    "卷號": "42",
    "篇號": "1149",
    "篇名": "所愛者為第一"
  },
  "起": "如是我聞：一時，佛住舍衛國祇樹給孤獨園。",
  "法": [
    "時，波斯匿王為首，并七國王及諸大臣悉共集會作如是論議：「五欲之中何者第一？」有一人言色最第一，又復有稱聲香味觸為第一者。中有人言：「我等人人各說第一，竟無定判，當詣世尊問如此義，如世尊說當共憶持。」爾時，波斯匿王為首與七國王、大臣、眷屬來詣佛所，稽首佛足，退坐一面，白佛言：「世尊！我等七王與諸大臣如是論議：『五欲功德何者為勝？』其中有言色勝、有言聲勝、有言香勝、有言味勝、有言觸勝，竟無決定，來問世尊竟何者勝？」",
    "佛告諸王：「各隨意適，我悉有餘說，以是因緣我說五欲功德，然自有人於色適意，止愛一色，滿其志願，正使過上有諸勝色，非其所愛，不觸不視，言己所愛最為第一，無過其上；如愛色者，聲香味觸亦皆如是，當其所愛輒言最勝，歡喜樂著，雖更有勝過其上者，非其所欲，不觸不視，唯我愛者最勝最妙，無比無上。」",
    "爾時座中有一優婆塞名曰栴檀從座起整衣服偏袒右肩合掌白佛：「善說！世尊！善說！善逝！」",
    "佛告優婆塞：「善說！栴檀！快說！栴檀！」",
    "時，栴檀優婆塞即說偈言：「央伽族姓王，服珠瓔珞鎧，摩竭眾慶集，如來出其國，名聞普流布，猶如雪山王，如淨水蓮華，清淨無瑕穢，隨日光開敷，芬香熏其國，央耆國明顯，猶如空中日，觀如來慧力，如夜然炬火，為眼為大明，來者為決疑。」",
    "時，諸國王歎言：「善說！栴檀優婆塞！」爾時，七王脫七寶上衣奉優婆塞。時，彼七王聞佛所說，歡喜隨喜，從座起去。",
    "爾時栴檀優婆塞知諸王去已，從座起整衣服偏袒右肩合掌白佛：「今七國王遺我七領上衣，唯願世尊受此七衣，以哀愍故！」"
  ],
  "結": "爾時，世尊為哀愍故受其七衣，栴檀優婆塞歡喜隨喜，作禮而去。",
  "fu": {
    "摘": "有人於色適意，止愛一色，滿其志願，正使過上有諸勝色，非其所愛，不觸不視，言己所愛最為第一，無過其上；如愛色者，聲香味觸亦皆如是，當其所愛輒言最勝，歡喜樂著，雖更有勝過其上者，非其所欲，不觸不視，唯我愛者最勝最妙，無比無上。"
  }
}