{
  "ps": {
    "卷號": "17",
    "篇號": "489",
    "篇名": "無常故當捨離"
  },
  "起": "如是我聞：一時，佛住王舍城迦蘭陀竹園，爾時，世尊告諸比丘：",
  "法": [
    "若於一法觀察無常、觀察變易、觀察離欲、觀察滅、觀察捨離，究竟苦邊，解脫於苦，謂一切眾生由食存。",
    "復有二法，名及色。",
    "復有三法，謂三受。",
    "復有四法，謂四食。",
    "復有五法，謂五受陰。",
    "復有六法，謂六內外入處。",
    "復有七法，謂七識住。",
    "復有八法，謂世八法。",
    "復有九法，謂九眾生居。",
    "復有十法，謂十業跡，於此十業跡觀察無常、觀察變易、觀察離欲、觀察滅、觀察捨離，究竟苦邊，解脫於苦。"
  ],
  "結": "佛說此經已，諸比丘聞佛所說，歡喜奉行。",
  "fu": {
    "摘": "若於一法觀察無常、觀察變易、觀察離欲、觀察滅、觀察捨離，究竟苦邊，解脫於苦，謂一切眾生由食存。復有二法，名及色。復有三法，謂三受。復有四法，謂四食。復有五法，謂五受陰。復有六法，謂六內外入處。復有七法，謂七識住。復有八法，謂世八法。復有九法，謂九眾生居。復有十法，謂十業跡，於此十業跡觀察無常、觀察變易、觀察離欲、觀察滅、觀察捨離，究竟苦邊，解脫於苦。"
  }
}